MANIFEST.in
README.rst
importscript.py
setup.py
zopeskel.txt
collective/__init__.py
collective.plonetruegallery.egg-info/PKG-INFO
collective.plonetruegallery.egg-info/SOURCES.txt
collective.plonetruegallery.egg-info/dependency_links.txt
collective.plonetruegallery.egg-info/entry_points.txt
collective.plonetruegallery.egg-info/namespace_packages.txt
collective.plonetruegallery.egg-info/not-zip-safe
collective.plonetruegallery.egg-info/requires.txt
collective.plonetruegallery.egg-info/top_level.txt
collective/plonetruegallery/__init__.py
collective/plonetruegallery/behavior.zcml
collective/plonetruegallery/browser.txt
collective/plonetruegallery/config.py
collective/plonetruegallery/configlet.py
collective/plonetruegallery/configure.zcml
collective/plonetruegallery/exportimport.py
collective/plonetruegallery/gallery-portlet.pt
collective/plonetruegallery/i18n.sh
collective/plonetruegallery/interfaces.py
collective/plonetruegallery/portlets.py
collective/plonetruegallery/portlets.zcml
collective/plonetruegallery/profiles.zcml
collective/plonetruegallery/settings.py
collective/plonetruegallery/testing.py
collective/plonetruegallery/upgrades.py
collective/plonetruegallery/upgrades.zcml
collective/plonetruegallery/utils.py
collective/plonetruegallery/validators.py
collective/plonetruegallery/vocabularies.py
collective/plonetruegallery/browser/__init__.py
collective/plonetruegallery/browser/configure.zcml
collective/plonetruegallery/browser/interfaces.py
collective/plonetruegallery/browser/util.py
collective/plonetruegallery/browser/files/style.css
collective/plonetruegallery/browser/files/tile.png
collective/plonetruegallery/browser/files/portlet/control.png
collective/plonetruegallery/browser/files/portlet/next.png
collective/plonetruegallery/browser/files/portlet/pause.png
collective/plonetruegallery/browser/files/portlet/play.png
collective/plonetruegallery/browser/files/portlet/portlet.css
collective/plonetruegallery/browser/files/portlet/portlet.js
collective/plonetruegallery/browser/files/portlet/prev.png
collective/plonetruegallery/browser/views/.DS_Store
collective/plonetruegallery/browser/views/__init__.py
collective/plonetruegallery/browser/views/collage.zcml
collective/plonetruegallery/browser/views/configure.zcml
collective/plonetruegallery/browser/views/display.py
collective/plonetruegallery/browser/views/galleryview.py
