Metadata-Version: 2.1
Name: collective.plonetruegallery
Version: 3.4.9
Summary: A gallery/slideshow product for Plone that can aggregate from Picasa (add collective.ptg.flickr) and Flickr (add collective.ptg.flickr) or use Plone images.
Home-page: https://github.com/collective/collective.plonetruegallery
Author: Nathan Van Gheem
Author-email: vangheem@gmail.com
License: UNKNOWN
Keywords: gallery plone slideshow photo photos image images picasa flickr highslide nivoslider nivogallery pikachoose fancybox supersized quicksandgalleriffic galleria
Platform: UNKNOWN
Classifier: Development Status :: 5 - Production/Stable
Classifier: Environment :: Web Environment
Classifier: Framework :: Plone :: 4.1
Classifier: Framework :: Plone :: 4.2
Classifier: Framework :: Plone :: 4.3
Classifier: Framework :: Plone
Classifier: License :: OSI Approved :: GNU General Public License (GPL)
Classifier: Operating System :: OS Independent
Classifier: Programming Language :: Python :: 2.6
Classifier: Programming Language :: Python :: 2.7
Classifier: Programming Language :: Python
Classifier: Topic :: Software Development :: Libraries :: Python Modules
Provides-Extra: test
